{
  "active": true,
  "address": "0x9a71012B13CA4d3D0Cdc72A177DF3ef03b0E76A3",
  "color": null,
  "decimals": 18,
  "description": null,
  "id": "d3b12edd-7bb4-4543-a32d-a390fa98ea34",
  "links": null,
  "logo": {
    "png": {
      "url": null,
      "ipfs": null
    },
    "svg": {
      "url": "https://raw.githubusercontent.com/map3xyz/polygon-tokenlist/master/0x9a71012B13CA4d3D0Cdc72A177DF3ef03b0E76A3/logo.svg",
      "ipfs": null
    }
  },
  "name": "Balancer",
  "networkId": "polygon",
  "spam": true,
  "symbol": "BAL",
  "tags": [
    "pos",
    "erc20",
    "swapable"
  ],
  "verifications": [],
  "version": "0.0.1"
}